nti/__init__.py
nti/schema/__init__.py
nti/schema/configure.zcml
nti/schema/eqhash.py
nti/schema/field.py
nti/schema/fieldproperty.py
nti/schema/interfaces.py
nti/schema/jsonschema.py
nti/schema/schema.py
nti/schema/subscribers.py
nti/schema/testing.py
nti/schema/vocabulary.py
nti/schema/locales/nti.dataserver.pot
nti/schema/locales/en/LC_MESSAGES/nti.dataserver.po
nti/schema/tests/__init__.py
nti/schema/tests/eqhash_benchmark.py
nti/schema/tests/test_eqhash.py
nti/schema/tests/test_field.py
nti/schema/tests/test_fieldproperty.py
nti/schema/tests/test_interfaces.py
nti/schema/tests/test_jsonschema.py
nti/schema/tests/test_schema.py
nti/schema/tests/test_vocabulary.py
nti_schema-1.19.0.dist-info/licenses/AUTHORS
nti_schema-1.19.0.dist-info/licenses/LICENSE
nti_schema-1.19.0.dist-info/METADATA
nti_schema-1.19.0.dist-info/WHEEL
nti_schema-1.19.0.dist-info/top_level.txt
nti_schema-1.19.0.dist-info/zip-safe
nti_schema-1.19.0.dist-info/RECORD
