Metadata-Version: 2.4
Name: nti.schema
Version: 1.19.0
Summary: Zope schema related support
Home-page: https://github.com/OpenNTI/nti.schema
Author: Jason Madden
Author-email: open-source@nextthought.com
License: Apache
Keywords: zope schema
Classifier: Development Status :: 5 - Production/Stable
Classifier: Intended Audience :: Developers
Classifier: License :: OSI Approved :: Apache Software License
Classifier: Natural Language :: English
Classifier: Operating System :: OS Independent
Classifier: Programming Language :: Python :: 3
Classifier: Programming Language :: Python :: 3 :: Only
Classifier: Programming Language :: Python :: 3.12
Classifier: Programming Language :: Python :: 3.13
Classifier: Programming Language :: Python :: 3.14
Classifier: Programming Language :: Python :: Implementation :: CPython
Classifier: Programming Language :: Python :: Implementation :: PyPy
Classifier: Framework :: Zope3
Requires-Python: >=3.12
License-File: LICENSE
License-File: AUTHORS
Requires-Dist: nti.i18n>=1.1.0
Requires-Dist: zope.event
Requires-Dist: zope.interface>=5.0.0
Requires-Dist: zope.schema>=6.0.0
Requires-Dist: zope.i18n>=4.7.0
Requires-Dist: zope.i18nmessageid
Requires-Dist: zope.vocabularyregistry>=1.1.1
Requires-Dist: zope.deprecation
Requires-Dist: zope.deferredimport>=4.2.1
Requires-Dist: zope.configuration>=4.4.0
Provides-Extra: test
Requires-Dist: pyhamcrest; extra == "test"
Requires-Dist: nti.testing; extra == "test"
Requires-Dist: zope.testrunner; extra == "test"
Requires-Dist: zope.component>=4.6.1; extra == "test"
Provides-Extra: docs
Requires-Dist: Sphinx; extra == "docs"
Requires-Dist: nti.testing; extra == "docs"
Requires-Dist: repoze.sphinx.autointerface; extra == "docs"
Requires-Dist: sphinx_rtd_theme; extra == "docs"
Requires-Dist: Acquisition; extra == "docs"
Dynamic: author
Dynamic: author-email
Dynamic: classifier
Dynamic: description
Dynamic: home-page
Dynamic: keywords
Dynamic: license
Dynamic: license-file
Dynamic: provides-extra
Dynamic: requires-dist
Dynamic: requires-python
Dynamic: summary
